asyncservo.py
asyncservo-0.0.1a1.dist-info/WHEEL
asyncservo-0.0.1a1.dist-info/METADATA
asyncservo-0.0.1a1.dist-info/RECORD
