Metadata-Version: 2.1
Name: asyncservo
Version: 0.0.1a1
Summary: asyncservo
Home-page: https://github.com/ollipal
License: UNKNOWN
Author: ollipal
Classifier: License :: OSI Approved :: MIT License
